ruson-1.0.6.dist-info/METADATA
ruson-1.0.6.dist-info/WHEEL
ruson/driver/results.py
ruson/driver/types.pyi
ruson/driver/client.py
ruson/driver/session.py
ruson/driver/collection.pyi
ruson/driver/__init__.py
ruson/driver/collection.py
ruson/driver/types.py
ruson/driver/client.pyi
ruson/driver/database.pyi
ruson/driver/results.pyi
ruson/driver/session.pyi
ruson/driver/database.py
ruson/py.typed
ruson/__init__.py
ruson/core/instance.py
ruson/core/config.py
ruson/core/__init__.py
ruson/core/ruson_doc.py
ruson/ruson.cpython-311-x86_64-linux-gnu.so
ruson-1.0.6.dist-info/RECORD
