Metadata-Version: 2.3
Name: ruson
Version: 1.0.6
Classifier: Programming Language :: Rust
Classifier: Programming Language :: Python :: Implementation :: CPython
Classifier: Programming Language :: Python :: Implementation :: PyPy
Requires-Dist: pydantic >=2.5
Requires-Dist: pytz
Requires-Dist: pytest ; extra == 'test'
Requires-Dist: pytest-asyncio ; extra == 'test'
Requires-Dist: colorama ; extra == 'test'
Provides-Extra: test
Summary: Asynchronous MongoDB Driver Wrapper For Rust MongoDB crate
Keywords: rust,mongo,driver,database
Author-email: João Severo <contato@gmail.com>
Requires-Python: >=3.11
